[
    {
        "image": "https://image.tmdb.org/t/p/original/TxbvYS8wsgYSpYZtQLZXnoVOIQ.jpg",
        "category": "Film Library",
        "title": "John Wick (2014)",
        "url": "https://gstream.hollymoviehd.cc/streamsvr/nENI74N9Xu/0-2"
    },
    {
        "image": "https://image.tmdb.org/t/p/original/3kcQOLwYKGPwyjiynFsvP8vHvRn.jpg",
        "category": "Film Library",
        "title": "September 5 (2024)",
        "url": "https://gstream.hollymoviehd.cc/streamsvr/khvcVXPVgP/0-1"
    },
    {
        "image": "https://image.tmdb.org/t/p/original/qFmwhVUoUSXjkKRmca5yGDEXBIj.jpg",
        "category": "Film Library",
        "title": "Spider-Man 3 (2007)",
        "url": "https://gstream.hollymoviehd.cc/streamsvr/AXMOHJVlLC/0-2"
    },
    {
        "image": "https://image.tmdb.org/t/p/original/79cNRSR2pedwsJ2szTdHQbj3RQs.jpg",
        "category": "Film Library",
        "title": "Bass Impact (2024)",
        "url": "https://gstream.hollymoviehd.cc/streamsvr/qUdpqPknQE/0-3"
    },
    {
        "image": "https://image.tmdb.org/t/p/original/jexoNYnPd6vVrmygwF6QZmWPFdu.jpg",
        "category": "Film Library",
        "title": "The Amazing Spider Man (2012)",
        "url": "https://gstream.hollymoviehd.cc/streamsvr/5D0mA-TZfe/0-4"
    }
]